k_counties/__init__.py
k_counties/kenya.py
k_counties/kenya_counties.txt
k_counties/read.py
kenya_counties-0.0.3.dist-info/LICENCE
kenya_counties-0.0.3.dist-info/METADATA
kenya_counties-0.0.3.dist-info/WHEEL
kenya_counties-0.0.3.dist-info/top_level.txt
kenya_counties-0.0.3.dist-info/RECORD
