Metadata-Version: 2.1
Name: kenya-counties
Version: 0.0.3
Summary: This package returns all kenya counties in list and the number of the counties
Home-page: https://github.com/john-maluki/kenyan_counties
Author: John Maluki
Author-email: johnmaluki58@gmail.com
License: UNKNOWN
Platform: UNKNOWN
Classifier: Programming Language :: Python :: 3
Classifier: License :: OSI Approved :: MIT License
Classifier: Operating System :: OS Independent
Requires-Python: >=3.6
